gecosistema_users/__init__.py
gecosistema_users/usersdb.py
gecosistema_users-0.0.15.dist-info/METADATA
gecosistema_users-0.0.15.dist-info/RECORD
gecosistema_users-0.0.15.dist-info/WHEEL
gecosistema_users-0.0.15.dist-info/top_level.txt
