Metadata-Version: 2.1
Name: gecosistema-users
Version: 0.0.15
Summary: A small example package
Home-page: https://github.com/valluzzi/gecosistema_users.git
Author: Valerio Luzzi
Author-email: valluzzi@gmail.com
License: UNKNOWN
Platform: UNKNOWN
Classifier: Programming Language :: Python :: 2
Classifier: License :: OSI Approved :: MIT License
Classifier: Operating System :: OS Independent
Requires-Dist: gecosistema-core
Requires-Dist: gecosistema-database
Requires-Dist: gecosistema-mail
